django_model_cache/__init__.py
django_model_cache/core.py
django_model_cache-1.0.1.dist-info/DESCRIPTION.rst
django_model_cache-1.0.1.dist-info/METADATA
django_model_cache-1.0.1.dist-info/RECORD
django_model_cache-1.0.1.dist-info/WHEEL
django_model_cache-1.0.1.dist-info/metadata.json
django_model_cache-1.0.1.dist-info/top_level.txt
